berryworld/__init__.py
berryworld/aks_logs.py
berryworld/allocation_solver.py
berryworld/app_logs.py
berryworld/app_logs_query.py
berryworld/cache_data.py
berryworld/credentials.py
berryworld/devops.py
berryworld/email_con.py
berryworld/email_logging.py
berryworld/generate_env.py
berryworld/handy_mix.py
berryworld/logging.py
berryworld/logic_apps.py
berryworld/microsoft_teams.py
berryworld/persistent_storage.py
berryworld/pickle_management.py
berryworld/power_automate.py
berryworld/python_logs.py
berryworld/sharepoint_con.py
berryworld/snowflake_conn.py
berryworld/sql_conn.py
berryworld/sql_connection.py
berryworld/teams_logging.py
berryworld/transportation_solver.py
berryworld/verify_keys.py
berryworld/vivantio.py
berryworld/vivantio_logging.py
berryworld/xml_parser.py
berryworld-1.0.0.199449.dist-info/licenses/LICENSE
tests/__init__.py
tests/test_allocation_config.py
tests/test_handy_mix_config.py
tests/test_xml_parser.py
berryworld-1.0.0.199449.dist-info/METADATA
berryworld-1.0.0.199449.dist-info/WHEEL
berryworld-1.0.0.199449.dist-info/top_level.txt
berryworld-1.0.0.199449.dist-info/RECORD
