Metadata-Version: 2.4
Name: berryworld
Version: 1.0.0.199449
Summary: Handy classes to improve ETL processes
Home-page: https://www.berryworld.com
Author: BerryWorld ltd
Author-email: data@berryworld.com
Classifier: Programming Language :: Python :: 3
Classifier: License :: OSI Approved :: MIT License
Classifier: Operating System :: OS Independent
Requires-Python: >=3.11
License-File: LICENSE
Requires-Dist: azure-identity>=1.15.0
Requires-Dist: azure-keyvault-secrets>=4.8.0
Requires-Dist: cryptography>=3.4.8
Requires-Dist: msal>=1.14.0
Requires-Dist: numpy>=1.25.2
Requires-Dist: opencensus>=0.11.0
Requires-Dist: opencensus_ext_azure>=1.1.7
Requires-Dist: pandas>=1.4.2
Requires-Dist: pyodbc>=4.0.39
Requires-Dist: python-dotenv>=1.0.0
Requires-Dist: PyYAML>=6.0
Requires-Dist: requests>=2.31.0
Requires-Dist: scipy>=1.11.1
Requires-Dist: setuptools>=61.2.0
Requires-Dist: SQLAlchemy>=1.4.32
Requires-Dist: snowflake-connector-python>=3.12.2
Requires-Dist: snowflake>=0.12.1
Requires-Dist: cffi>=1.15.1
Requires-Dist: beautifulsoup4>=4.12.2
Dynamic: author
Dynamic: author-email
Dynamic: classifier
Dynamic: description
Dynamic: description-content-type
Dynamic: home-page
Dynamic: license-file
Dynamic: requires-dist
Dynamic: requires-python
Dynamic: summary
